kubeshell/__init__.py
kubeshell/app.py
kubeshell/client.py
kubeshell/completer.py
kubeshell/lexer.py
kubeshell/logger.py
kubeshell/main.py
kubeshell/parser.py
kubeshell/style.py
kubeshell/toolbar.py
kubeshell/utils.py
kubeshell/data/cli.json
ksh-0.1.0.dist-info/LICENSE
ksh-0.1.0.dist-info/METADATA
ksh-0.1.0.dist-info/WHEEL
ksh-0.1.0.dist-info/entry_points.txt
ksh-0.1.0.dist-info/top_level.txt
ksh-0.1.0.dist-info/RECORD
